cdf_queue/__main__.py
cdf_queue/multihandle.py
cdf_queue/multihandle_test.py
cdf_queue-0.0.2.dist-info/METADATA
cdf_queue-0.0.2.dist-info/WHEEL
cdf_queue-0.0.2.dist-info/RECORD
